odoo/addons/crowdfunding_public_pledge/README.rst
odoo/addons/crowdfunding_public_pledge/__init__.py
odoo/addons/crowdfunding_public_pledge/__manifest__.py
odoo/addons/crowdfunding_public_pledge/controllers/__init__.py
odoo/addons/crowdfunding_public_pledge/controllers/payment.py
odoo/addons/crowdfunding_public_pledge/i18n/crowdfunding_public_pledge.pot
odoo/addons/crowdfunding_public_pledge/models/__init__.py
odoo/addons/crowdfunding_public_pledge/models/account_move.py
odoo/addons/crowdfunding_public_pledge/models/crowdfunding_challenge.py
odoo/addons/crowdfunding_public_pledge/readme/CONTRIBUTORS.md
odoo/addons/crowdfunding_public_pledge/readme/DESCRIPTION.md
odoo/addons/crowdfunding_public_pledge/readme/USAGE.md
odoo/addons/crowdfunding_public_pledge/static/description/icon.png
odoo/addons/crowdfunding_public_pledge/static/description/index.html
odoo/addons/crowdfunding_public_pledge/templates/crowdfunding_challenge.xml
odoo/addons/crowdfunding_public_pledge/templates/payment.xml
odoo/addons/crowdfunding_public_pledge/views/account_move.xml
odoo14_addon_crowdfunding_public_pledge-14.0.1.0.1.dev2.dist-info/METADATA
odoo14_addon_crowdfunding_public_pledge-14.0.1.0.1.dev2.dist-info/WHEEL
odoo14_addon_crowdfunding_public_pledge-14.0.1.0.1.dev2.dist-info/top_level.txt
odoo14_addon_crowdfunding_public_pledge-14.0.1.0.1.dev2.dist-info/RECORD
